unmanic/__init__.py
unmanic/__main__.py
unmanic/config.py
unmanic/metadata.py
unmanic/service.py
unmanic/version
unmanic/libs/__init__.py
unmanic/libs/common.py
unmanic/libs/db_migrate.py
unmanic/libs/directoryinfo.py
unmanic/libs/eventmonitor.py
unmanic/libs/fileinfo.py
unmanic/libs/filetest.py
unmanic/libs/foreman.py
unmanic/libs/frontend_push_messages.py
unmanic/libs/history.py
unmanic/libs/installation_link.py
unmanic/libs/library.py
unmanic/libs/libraryscanner.py
unmanic/libs/logs.py
unmanic/libs/notifications.py
unmanic/libs/plugins.py
unmanic/libs/postprocessor.py
unmanic/libs/scheduler.py
unmanic/libs/session.py
unmanic/libs/singleton.py
unmanic/libs/system.py
unmanic/libs/task.py
unmanic/libs/taskhandler.py
unmanic/libs/taskqueue.py
unmanic/libs/uiserver.py
unmanic/libs/worker_group.py
unmanic/libs/workers.py
unmanic/libs/unffmpeg/__init__.py
unmanic/libs/unffmpeg/audio_codec_handle.py
unmanic/libs/unffmpeg/base_codecs.py
unmanic/libs/unffmpeg/base_containers.py
unmanic/libs/unffmpeg/hardware_acceleration_handle.py
unmanic/libs/unffmpeg/info.py
unmanic/libs/unffmpeg/subtitle_handle.py
unmanic/libs/unffmpeg/video_codec_handle.py
unmanic/libs/unffmpeg/audio_codecs/__init__.py
unmanic/libs/unffmpeg/audio_codecs/aac.py
unmanic/libs/unffmpeg/audio_codecs/ac3.py
unmanic/libs/unffmpeg/audio_codecs/mp3.py
unmanic/libs/unffmpeg/containers/__init__.py
unmanic/libs/unffmpeg/containers/avi.py
unmanic/libs/unffmpeg/containers/flv.py
unmanic/libs/unffmpeg/containers/matroska.py
unmanic/libs/unffmpeg/containers/mov.py
unmanic/libs/unffmpeg/containers/mp4.py
unmanic/libs/unffmpeg/containers/mpeg.py
unmanic/libs/unffmpeg/containers/mpegts.py
unmanic/libs/unffmpeg/containers/ogv.py
unmanic/libs/unffmpeg/containers/psp.py
unmanic/libs/unffmpeg/containers/vob.py
unmanic/libs/unffmpeg/exceptions/__init__.py
unmanic/libs/unffmpeg/exceptions/ffmpeg.py
unmanic/libs/unffmpeg/exceptions/ffprobe.py
unmanic/libs/unffmpeg/lib/__init__.py
unmanic/libs/unffmpeg/lib/cli.py
unmanic-0.3.0.post35.dist-info/licenses/LICENSE
unmanic-0.3.0.post35.dist-info/METADATA
unmanic-0.3.0.post35.dist-info/WHEEL
unmanic-0.3.0.post35.dist-info/entry_points.txt
unmanic-0.3.0.post35.dist-info/top_level.txt
unmanic-0.3.0.post35.dist-info/RECORD
