Metadata-Version: 2.4
Name: unmanic
Version: 0.3.0.post35
Summary: A simple tool for optimising your video library to a single format
Home-page: https://github.com/Josh5/unmanic
Author: Josh.5
Author-email: jsunnex@gmail.com
Maintainer: Josh.5
Maintainer-email: jsunnex@gmail.com
License: GPL-3.0-only
Classifier: Development Status :: 5 - Production/Stable
Classifier: Intended Audience :: End Users/Desktop
Classifier: Intended Audience :: Developers
Classifier: Programming Language :: Python :: 3.8
Classifier: Programming Language :: Python :: 3.9
Classifier: Programming Language :: Python :: 3.10
Classifier: Programming Language :: Python :: 3.11
Classifier: Programming Language :: Python :: 3.12
Classifier: Operating System :: POSIX :: Linux
Classifier: Operating System :: Unix
Classifier: Topic :: Multimedia :: Video :: Conversion
Classifier: Topic :: Internet :: WWW/HTTP
Requires-Python: >=3.8
License-File: LICENSE
Requires-Dist: schedule==1.2.2
Requires-Dist: tornado==6.3.3
Requires-Dist: marshmallow~=3.22
Requires-Dist: peewee>=3.14.4
Requires-Dist: peewee_migrate==1.13.0
Requires-Dist: psutil~=6.0.0
Requires-Dist: requests>=2.28.2
Requires-Dist: requests_toolbelt>=0.9.1
Requires-Dist: py-cpuinfo>=7.0.0
Requires-Dist: JSON-log-formatter~=0.5.2
Requires-Dist: watchdog>=2.1.1
Requires-Dist: inquirer>=2.7.0
Requires-Dist: swagger-ui-py
Provides-Extra: dev
Requires-Dist: flake8>=5.0.4; extra == "dev"
Requires-Dist: pycodestyle>=2.9.1; extra == "dev"
Requires-Dist: pytest>=7.4.3; extra == "dev"
Requires-Dist: wheel>=0.42.0; extra == "dev"
Requires-Dist: setuptools>=68.0.0; extra == "dev"
Requires-Dist: build>=0.10.0; extra == "dev"
Requires-Dist: apispec>=6.3.1; extra == "dev"
Requires-Dist: apispec_webframeworks>=0.5.2; extra == "dev"
Requires-Dist: pyyaml>=6.0.1; extra == "dev"
Dynamic: author
Dynamic: author-email
Dynamic: classifier
Dynamic: home-page
Dynamic: license
Dynamic: license-file
Dynamic: maintainer
Dynamic: maintainer-email
Dynamic: provides-extra
Dynamic: requires-dist
Dynamic: summary
